appletree/__init__.py
appletree/component.py
appletree/components/__init__.py
appletree/components/ac.py
appletree/components/er.py
appletree/components/nr.py
appletree/components/yields.py
appletree/config.py
appletree/context.py
appletree/contexts/__init__.py
appletree/contexts/er_only.py
appletree/data/AC_Rn220.pkl
appletree/data/data_Ar37.csv
appletree/data/data_Neutron.csv
appletree/data/data_Rn220.csv
appletree/hist.py
appletree/instructs/literature_lyqy.json
appletree/instructs/neutron_low.json
appletree/instructs/rn220.json
appletree/instructs/rn220_ar37.json
appletree/interpolation.py
appletree/likelihood.py
appletree/maps/_3fold_recon_eff.json
appletree/maps/_elife.json
appletree/maps/_gas_gain_relative.json
appletree/maps/_nr_ly.json
appletree/maps/_nr_qy.json
appletree/maps/_nr_spectrum.json
appletree/maps/_posrec_reso.json
appletree/maps/_s1_bias.json
appletree/maps/_s1_correction.json
appletree/maps/_s1_cut_acc.json
appletree/maps/_s1_smearing.json
appletree/maps/_s2_bias.json
appletree/maps/_s2_correction.json
appletree/maps/_s2_cut_acc.json
appletree/maps/_s2_smearing.json
appletree/parameter.py
appletree/parameters/er.json
appletree/parameters/er_rn220_ar37.json
appletree/parameters/nestv2.json
appletree/parameters/nestv2_yield_only.json
appletree/parameters/nr_low.json
appletree/plot.py
appletree/plugin.py
appletree/plugins/__init__.py
appletree/plugins/common.py
appletree/plugins/detector.py
appletree/plugins/efficiency.py
appletree/plugins/er_microphys.py
appletree/plugins/lyqy.py
appletree/plugins/nestv2.py
appletree/plugins/reconstruction.py
appletree/randgen.py
appletree/share.py
appletree/utils.py
appletree-0.5.4.dist-info/LICENSE
appletree-0.5.4.dist-info/METADATA
appletree-0.5.4.dist-info/WHEEL
appletree-0.5.4.dist-info/entry_points.txt
appletree-0.5.4.dist-info/RECORD
